LICENSE.txt
MANIFEST.in
setup.cfg
setup.py
purity_fb/README.md
purity_fb/__init__.py
purity_fb/api.py
purity_fb/api_client.py
purity_fb/configuration.py
purity_fb/fb_client.py
purity_fb/rest.py
purity_fb.egg-info/PKG-INFO
purity_fb.egg-info/SOURCES.txt
purity_fb.egg-info/dependency_links.txt
purity_fb.egg-info/requires.txt
purity_fb.egg-info/top_level.txt
purity_fb/api_client/__init__.py
purity_fb/api_client/api_client.py
purity_fb/api_client/configuration.py
purity_fb/api_client/rest.py
purity_fb/api_client/version_api.py
purity_fb/api_client/models/__init__.py
purity_fb/api_client/models/error_response.py
purity_fb/api_client/models/login_response.py
purity_fb/api_client/models/object_response.py
purity_fb/api_client/models/pagination_info.py
purity_fb/api_client/models/pure_error.py
purity_fb/api_client/models/pure_object.py
purity_fb/api_client/models/version_response.py
purity_fb/purity_fb_1dot0/__init__.py
purity_fb/purity_fb_1dot0/api_client.py
purity_fb/purity_fb_1dot0/configuration.py
purity_fb/purity_fb_1dot0/rest.py
purity_fb/purity_fb_1dot0/apis/__init__.py
purity_fb/purity_fb_1dot0/apis/authentication_api.py
purity_fb/purity_fb_1dot0/apis/file_system_snapshots_api.py
purity_fb/purity_fb_1dot0/apis/file_systems_api.py
purity_fb/purity_fb_1dot0/apis/version_api.py
purity_fb/purity_fb_1dot0/models/__init__.py
purity_fb/purity_fb_1dot0/models/error_response.py
purity_fb/purity_fb_1dot0/models/file_system.py
purity_fb/purity_fb_1dot0/models/file_system_response.py
purity_fb/purity_fb_1dot0/models/file_system_snapshot.py
purity_fb/purity_fb_1dot0/models/file_system_snapshot_response.py
purity_fb/purity_fb_1dot0/models/login_response.py
purity_fb/purity_fb_1dot0/models/nfs_rule.py
purity_fb/purity_fb_1dot0/models/object_response.py
purity_fb/purity_fb_1dot0/models/pagination_info.py
purity_fb/purity_fb_1dot0/models/protocol_rule.py
purity_fb/purity_fb_1dot0/models/pure_error.py
purity_fb/purity_fb_1dot0/models/pure_object.py
purity_fb/purity_fb_1dot0/models/smb_rule.py
purity_fb/purity_fb_1dot0/models/snapshot_suffix.py
purity_fb/purity_fb_1dot0/models/space.py
purity_fb/purity_fb_1dot0/models/version_response.py
