Metadata-Version: 1.0
Name: purity-fb
Version: 1.12.3
Summary: Pure Storage FlashBlade REST 1.12 Python SDK
Home-page: UNKNOWN
Author: UNKNOWN
Author-email: info@purestorage.com
License: UNKNOWN
Keywords: Swagger,Purity//FB REST Client
Platform: UNKNOWN
